setup.py
Tic_Tac_Toe/Game.py
Tic_Tac_Toe/Game_Rule.py
Tic_Tac_Toe/Game_board.py
Tic_Tac_Toe/__init__.py
sh_Tic_Tac_Toe.egg-info/PKG-INFO
sh_Tic_Tac_Toe.egg-info/SOURCES.txt
sh_Tic_Tac_Toe.egg-info/dependency_links.txt
sh_Tic_Tac_Toe.egg-info/not-zip-safe
sh_Tic_Tac_Toe.egg-info/top_level.txt