Metadata-Version: 1.0
Name: sh-Tic-Tac-Toe
Version: 0.1
Summary: Tic_Tac_Toe
Home-page: UNKNOWN
Author: Shuyi Huo
Author-email: UNKNOWN
License: UNKNOWN
Platform: UNKNOWN
